darq/__init__.py
darq/app.py
darq/cli.py
darq/connections.py
darq/constants.py
darq/cron.py
darq/jobs.py
darq/logs.py
darq/py.typed
darq/registry.py
darq/scheduler.py
darq/types.py
darq/utils.py
darq/version.py
darq/worker.py
darq-0.11.2.data/data/CHANGES.rst
darq-0.11.2.dist-info/LICENSE
darq-0.11.2.dist-info/METADATA
darq-0.11.2.dist-info/WHEEL
darq-0.11.2.dist-info/entry_points.txt
darq-0.11.2.dist-info/top_level.txt
darq-0.11.2.dist-info/RECORD
