Metadata-Version: 2.1
Name: darq
Version: 0.11.2
Summary: Async task manager with Celery-like features and type checking. Fork of arq.
Home-page: https://github.com/seedofjoy/darq
Author: Igor Mozharovsky
Author-email: igor.mozharovsky@gmail.com
License: MIT
Classifier: Environment :: Console
Classifier: License :: OSI Approved :: MIT License
Classifier: Operating System :: OS Independent
Classifier: Programming Language :: Python :: 3
Classifier: Programming Language :: Python :: 3.7
Classifier: Programming Language :: Python :: 3.8
Classifier: Programming Language :: Python :: 3.9
Classifier: Programming Language :: Python :: 3.10
Classifier: Programming Language :: Python :: 3.11
Classifier: Typing :: Typed
Requires-Python: >=3.7
License-File: LICENSE
Requires-Dist: async-timeout <5.0,>=3.0.0
Requires-Dist: click >=6.7
Requires-Dist: typing-extensions >=4.0 ; python_version < "3.8"
Provides-Extra: watch
Requires-Dist: watchgod >=0.4 ; extra == 'watch'
